Metadata-Version: 1.0
Name: mcbizmod
Version: 0.0.1
Summary: Distribution-based business cases.
Home-page: https://github.com/cvs-health/mcbizmod
Author: Eugenio Zuccarelli, Eli Goldberg
Author-email: eugenio.zuccarelli@gmail.com, zuccarellie@aetna.com, goldberge@cvshealth.com
License: UNKNOWN
Platform: UNKNOWN
